{
    "level": 14,
    "health": 111,
    "class": "dexterity",
    "dexterity": 4,
    "strength": 3,
    "constitution": 1,
    "intelligence": 1,
    "wisdom": 1,
    "charisma": 0,
    "save": {
        "dexterity": 9,
        "strength": 8,
        "constitution": 1,
        "intelligence": 1,
        "wisdom": 2,
        "charisma": 0
    },
    "skill": {
        "acrobatics": 4,
        "animal-handling": 6,
        "arcana": 1,
        "athletics": 8,
        "deception": 0,
        "history": 1,
        "insight": 1,
        "intimidation": 0,
        "investigation": 6,
        "medicine": 4,
        "nature": 6,
        "perception": 6,
        "performance": 0,
        "persuasion": 0,
        "religion": 1,
        "sleight-of-hand": 4,
        "stealth": 9,
        "survival": 6
    },
    "equipment": {
        "oathbow": {
            "hit": 11,
            "dmg_dice": "1d8",
            "dmg_mod": 6
        },
        "dagger": {
            "hit": 10,
            "dmg_dice": "1d4",
            "dmg_mod": 5
        },
        "greatsword": {
            "hit": 11,
            "dmg_dice": "2d6",
            "dmg_mod": 6
        },
        "handaxe": {
            "hit": 8,
            "dmg_dice": "1d6",
            "dmg_mod": 3
        },
        "unarmed": {
            "hit": 8,
            "dmg_dice": "None",
            "dmg_mod": 4
        }
    }
}